bumble/__init__.py
bumble/_version.py
bumble/a2dp.py
bumble/at.py
bumble/att.py
bumble/avc.py
bumble/avctp.py
bumble/avdtp.py
bumble/avrcp.py
bumble/bridge.py
bumble/codecs.py
bumble/colors.py
bumble/company_ids.py
bumble/controller.py
bumble/core.py
bumble/data_types.py
bumble/decoder.py
bumble/device.py
bumble/gap.py
bumble/gatt.py
bumble/gatt_adapters.py
bumble/gatt_client.py
bumble/gatt_server.py
bumble/hci.py
bumble/helpers.py
bumble/hfp.py
bumble/hid.py
bumble/host.py
bumble/keys.py
bumble/l2cap.py
bumble/link.py
bumble/ll.py
bumble/lmp.py
bumble/logging.py
bumble/pairing.py
bumble/py.typed
bumble/rfcomm.py
bumble/rtp.py
bumble/sdp.py
bumble/smp.py
bumble/snoop.py
bumble/utils.py
bumble/apps/README.md
bumble/apps/__init__.py
bumble/apps/auracast.py
bumble/apps/bench.py
bumble/apps/ble_rpa_tool.py
bumble/apps/console.py
bumble/apps/controller_info.py
bumble/apps/controller_loopback.py
bumble/apps/controllers.py
bumble/apps/device_info.py
bumble/apps/gatt_dump.py
bumble/apps/gg_bridge.py
bumble/apps/hci_bridge.py
bumble/apps/l2cap_bridge.py
bumble/apps/pair.py
bumble/apps/pandora_server.py
bumble/apps/rfcomm_bridge.py
bumble/apps/scan.py
bumble/apps/show.py
bumble/apps/unbond.py
bumble/apps/usb_probe.py
bumble/apps/lea_unicast/app.py
bumble/apps/lea_unicast/index.html
bumble/apps/player/player.py
bumble/apps/speaker/__init__.py
bumble/apps/speaker/logo.svg
bumble/apps/speaker/speaker.css
bumble/apps/speaker/speaker.html
bumble/apps/speaker/speaker.js
bumble/apps/speaker/speaker.py
bumble/audio/__init__.py
bumble/audio/io.py
bumble/crypto/__init__.py
bumble/crypto/builtin.py
bumble/crypto/cryptography.py
bumble/drivers/__init__.py
bumble/drivers/common.py
bumble/drivers/intel.py
bumble/drivers/rtk.py
bumble/pandora/__init__.py
bumble/pandora/config.py
bumble/pandora/device.py
bumble/pandora/host.py
bumble/pandora/l2cap.py
bumble/pandora/py.typed
bumble/pandora/security.py
bumble/pandora/utils.py
bumble/profiles/__init__.py
bumble/profiles/aics.py
bumble-0.0.223.dist-info/licenses/LICENSE
bumble-0.0.223.dist-info/METADATA
bumble-0.0.223.dist-info/WHEEL
bumble-0.0.223.dist-info/entry_points.txt
bumble-0.0.223.dist-info/top_level.txt
bumble-0.0.223.dist-info/RECORD
